MENDER/MENDER.py
MENDER/__init__.py
MENDER/utils.py
MENDER/voronoi.py
SOMENDER-1.1.dist-info/METADATA
SOMENDER-1.1.dist-info/WHEEL
SOMENDER-1.1.dist-info/top_level.txt
SOMENDER-1.1.dist-info/RECORD
